tests/__init__.py
tests/test_say_hello.py
yadu4ever/__init__.py
yadu4ever-0.0.2.dist-info/licenses/LICENSE.txt
yadu4ever-0.0.2.dist-info/METADATA
yadu4ever-0.0.2.dist-info/WHEEL
yadu4ever-0.0.2.dist-info/top_level.txt
yadu4ever-0.0.2.dist-info/RECORD
